macaroonbakery/__init__.py
macaroonbakery/_utils/__init__.py
macaroonbakery/bakery/__init__.py
macaroonbakery/bakery/_authorizer.py
macaroonbakery/bakery/_bakery.py
macaroonbakery/bakery/_checker.py
macaroonbakery/bakery/_codec.py
macaroonbakery/bakery/_discharge.py
macaroonbakery/bakery/_error.py
macaroonbakery/bakery/_identity.py
macaroonbakery/bakery/_keys.py
macaroonbakery/bakery/_macaroon.py
macaroonbakery/bakery/_oven.py
macaroonbakery/bakery/_store.py
macaroonbakery/bakery/_third_party.py
macaroonbakery/bakery/_versions.py
macaroonbakery/bakery/_internal/__init__.py
macaroonbakery/bakery/_internal/id_pb2.py
macaroonbakery/checkers/__init__.py
macaroonbakery/checkers/_auth_context.py
macaroonbakery/checkers/_caveat.py
macaroonbakery/checkers/_checkers.py
macaroonbakery/checkers/_conditions.py
macaroonbakery/checkers/_declared.py
macaroonbakery/checkers/_namespace.py
macaroonbakery/checkers/_operation.py
macaroonbakery/checkers/_time.py
macaroonbakery/checkers/_utils.py
macaroonbakery/httpbakery/__init__.py
macaroonbakery/httpbakery/_browser.py
macaroonbakery/httpbakery/_client.py
macaroonbakery/httpbakery/_discharge.py
macaroonbakery/httpbakery/_error.py
macaroonbakery/httpbakery/_interactor.py
macaroonbakery/httpbakery/_keyring.py
macaroonbakery/httpbakery/agent/__init__.py
macaroonbakery/httpbakery/agent/_agent.py
macaroonbakery/tests/__init__.py
macaroonbakery/tests/common.py
macaroonbakery/tests/test_agent.py
macaroonbakery/tests/test_authorizer.py
macaroonbakery/tests/test_bakery.py
macaroonbakery/tests/test_checker.py
macaroonbakery/tests/test_checkers.py
macaroonbakery/tests/test_client.py
macaroonbakery/tests/test_codec.py
macaroonbakery/tests/test_discharge.py
macaroonbakery/tests/test_discharge_all.py
macaroonbakery/tests/test_httpbakery.py
macaroonbakery/tests/test_keyring.py
macaroonbakery/tests/test_macaroon.py
macaroonbakery/tests/test_namespace.py
macaroonbakery/tests/test_oven.py
macaroonbakery/tests/test_store.py
macaroonbakery-1.3.4.dist-info/AUTHORS.rst
macaroonbakery-1.3.4.dist-info/LICENSE
macaroonbakery-1.3.4.dist-info/METADATA
macaroonbakery-1.3.4.dist-info/WHEEL
macaroonbakery-1.3.4.dist-info/top_level.txt
macaroonbakery-1.3.4.dist-info/RECORD
