Metadata-Version: 2.1
Name: macaroonbakery
Version: 1.3.4
Summary: A Python library port for bakery, higher level operation to work with macaroons
Home-page: https://github.com/go-macaroon-bakery/py-macaroon-bakery
Author: Juju UI Team
Author-email: juju-gui@lists.ubuntu.com
License: LGPL3
Keywords: macaroon cookie
Platform: UNKNOWN
Classifier: Development Status :: 2 - Pre-Alpha
Classifier: Intended Audience :: Developers
Classifier: License :: OSI Approved :: GNU Lesser General Public License v3 (LGPLv3)
Classifier: Natural Language :: English
Classifier: Programming Language :: Python :: 2
Classifier: Programming Language :: Python :: 2.7
Classifier: Programming Language :: Python :: 3
Classifier: Programming Language :: Python :: 3.5
License-File: LICENSE
License-File: AUTHORS.rst
